Prachi1305/mypkg.py
Prachi1305-0.0.0.dist-info/METADATA
Prachi1305-0.0.0.dist-info/WHEEL
Prachi1305-0.0.0.dist-info/top_level.txt
Prachi1305-0.0.0.dist-info/RECORD
