Metadata-Version: 2.1
Name: Prachi1305
Version: 0.0.0
Summary: My Package
Home-page: UNKNOWN
Author: UNKNOWN
Author-email: UNKNOWN
License: UNKNOWN
Platform: UNKNOWN
